certbot_dnspod/__init__.py
certbot_dnspod-0.1.4.dist-info/LICENSE
certbot_dnspod-0.1.4.dist-info/METADATA
certbot_dnspod-0.1.4.dist-info/WHEEL
certbot_dnspod-0.1.4.dist-info/entry_points.txt
certbot_dnspod-0.1.4.dist-info/RECORD
