Metadata-Version: 2.1
Name: certbot-dnspod
Version: 0.1.4
Summary: A certbot plugin for DNSPod
Home-page: https://github.com/codeif/certbot-dnspod
License: BSD-3-Clause
Author: codeif
Author-email: me@codeif.com
Requires-Python: >=3.9,<4.0
Classifier: License :: OSI Approved :: BSD License
Classifier: Programming Language :: Python :: 3
Classifier: Programming Language :: Python :: 3.9
Classifier: Programming Language :: Python :: 3.10
Classifier: Programming Language :: Python :: 3.11
Classifier: Programming Language :: Python :: 3.12
Classifier: Programming Language :: Python :: 3.13
Requires-Dist: certbot (>=3.0.1,<4.0.0)
Requires-Dist: dnspod-sdk (>=0.0.2,<0.0.3)
Requires-Dist: zope.interface (>=7.2,<8.0)
Project-URL: Repository, https://github.com/codeif/certbot-dnspod
